{"nodes": [{"id": "c_users_zero_documents_coding_zterm_crates_zterm_util_src_on_cancel_tests_rs", "label": "on_cancel_tests.rs", "file_type": "code", "source_file": "C:\\Users\\Zero\\Documents\\coding\\Zterm\\crates\\zterm_util\\src\\on_cancel_tests.rs", "source_location": "L1"}, {"id": "src_on_cancel_tests_test_ready_future_doesnt_call_callback", "label": "test_ready_future_doesnt_call_callback()", "file_type": "code", "source_file": "C:\\Users\\Zero\\Documents\\coding\\Zterm\\crates\\zterm_util\\src\\on_cancel_tests.rs", "source_location": "L6"}, {"id": "src_on_cancel_tests_test_aborted_future_calls_callback", "label": "test_aborted_future_calls_callback()", "file_type": "code", "source_file": "C:\\Users\\Zero\\Documents\\coding\\Zterm\\crates\\zterm_util\\src\\on_cancel_tests.rs", "source_location": "L16"}], "edges": [{"source": "c_users_zero_documents_coding_zterm_crates_zterm_util_src_on_cancel_tests_rs", "target": "oncancelfutureext", "relation": "imports_from", "confidence": "EXTRACTED", "source_file": "C:\\Users\\Zero\\Documents\\coding\\Zterm\\crates\\zterm_util\\src\\on_cancel_tests.rs", "source_location": "L1", "weight": 1.0}, {"source": "c_users_zero_documents_coding_zterm_crates_zterm_util_src_on_cancel_tests_rs", "target": "future", "relation": "imports_from", "confidence": "EXTRACTED", "source_file": "C:\\Users\\Zero\\Documents\\coding\\Zterm\\crates\\zterm_util\\src\\on_cancel_tests.rs", "source_location": "L2", "weight": 1.0}, {"source": "c_users_zero_documents_coding_zterm_crates_zterm_util_src_on_cancel_tests_rs", "target": "atomic", "relation": "imports_from", "confidence": "EXTRACTED", "source_file": "C:\\Users\\Zero\\Documents\\coding\\Zterm\\crates\\zterm_util\\src\\on_cancel_tests.rs", "source_location": "L3", "weight": 1.0}, {"source": "c_users_zero_documents_coding_zterm_crates_zterm_util_src_on_cancel_tests_rs", "target": "src_on_cancel_tests_test_ready_future_doesnt_call_callback", "relation": "contains", "confidence": "EXTRACTED", "source_file": "C:\\Users\\Zero\\Documents\\coding\\Zterm\\crates\\zterm_util\\src\\on_cancel_tests.rs", "source_location": "L6", "weight": 1.0}, {"source": "c_users_zero_documents_coding_zterm_crates_zterm_util_src_on_cancel_tests_rs", "target": "src_on_cancel_tests_test_aborted_future_calls_callback", "relation": "contains", "confidence": "EXTRACTED", "source_file": "C:\\Users\\Zero\\Documents\\coding\\Zterm\\crates\\zterm_util\\src\\on_cancel_tests.rs", "source_location": "L16", "weight": 1.0}], "raw_calls": [{"caller_nid": "src_on_cancel_tests_test_ready_future_doesnt_call_callback", "callee": "new", "is_member_call": false, "source_file": "C:\\Users\\Zero\\Documents\\coding\\Zterm\\crates\\zterm_util\\src\\on_cancel_tests.rs", "source_location": "L7"}, {"caller_nid": "src_on_cancel_tests_test_ready_future_doesnt_call_callback", "callee": "on_cancel", "is_member_call": true, "source_file": "C:\\Users\\Zero\\Documents\\coding\\Zterm\\crates\\zterm_util\\src\\on_cancel_tests.rs", "source_location": "L9"}, {"caller_nid": "src_on_cancel_tests_test_ready_future_doesnt_call_callback", "callee": "store", "is_member_call": true, "source_file": "C:\\Users\\Zero\\Documents\\coding\\Zterm\\crates\\zterm_util\\src\\on_cancel_tests.rs", "source_location": "L9"}, {"caller_nid": "src_on_cancel_tests_test_ready_future_doesnt_call_callback", "callee": "block_on", "is_member_call": false, "source_file": "C:\\Users\\Zero\\Documents\\coding\\Zterm\\crates\\zterm_util\\src\\on_cancel_tests.rs", "source_location": "L10"}, {"caller_nid": "src_on_cancel_tests_test_aborted_future_calls_callback", "callee": "new", "is_member_call": false, "source_file": "C:\\Users\\Zero\\Documents\\coding\\Zterm\\crates\\zterm_util\\src\\on_cancel_tests.rs", "source_location": "L17"}, {"caller_nid": "src_on_cancel_tests_test_aborted_future_calls_callback", "callee": "new_pair", "is_member_call": false, "source_file": "C:\\Users\\Zero\\Documents\\coding\\Zterm\\crates\\zterm_util\\src\\on_cancel_tests.rs", "source_location": "L19"}, {"caller_nid": "src_on_cancel_tests_test_aborted_future_calls_callback", "callee": "new", "is_member_call": false, "source_file": "C:\\Users\\Zero\\Documents\\coding\\Zterm\\crates\\zterm_util\\src\\on_cancel_tests.rs", "source_location": "L20"}, {"caller_nid": "src_on_cancel_tests_test_aborted_future_calls_callback", "callee": "on_cancel", "is_member_call": true, "source_file": "C:\\Users\\Zero\\Documents\\coding\\Zterm\\crates\\zterm_util\\src\\on_cancel_tests.rs", "source_location": "L21"}, {"caller_nid": "src_on_cancel_tests_test_aborted_future_calls_callback", "callee": "store", "is_member_call": true, "source_file": "C:\\Users\\Zero\\Documents\\coding\\Zterm\\crates\\zterm_util\\src\\on_cancel_tests.rs", "source_location": "L21"}, {"caller_nid": "src_on_cancel_tests_test_aborted_future_calls_callback", "callee": "abort", "is_member_call": true, "source_file": "C:\\Users\\Zero\\Documents\\coding\\Zterm\\crates\\zterm_util\\src\\on_cancel_tests.rs", "source_location": "L26"}, {"caller_nid": "src_on_cancel_tests_test_aborted_future_calls_callback", "callee": "block_on", "is_member_call": false, "source_file": "C:\\Users\\Zero\\Documents\\coding\\Zterm\\crates\\zterm_util\\src\\on_cancel_tests.rs", "source_location": "L27"}]}