{"nodes": [{"id": "c_users_zero_documents_coding_zterm_app_src_context_chips_directory_fetcher_tests_rs", "label": "directory_fetcher_tests.rs", "file_type": "code", "source_file": "C:\\Users\\Zero\\Documents\\coding\\Zterm\\app\\src\\context_chips\\directory_fetcher_tests.rs", "source_location": "L1"}, {"id": "context_chips_directory_fetcher_tests_create_directory_item", "label": "create_directory_item()", "file_type": "code", "source_file": "C:\\Users\\Zero\\Documents\\coding\\Zterm\\app\\src\\context_chips\\directory_fetcher_tests.rs", "source_location": "L3"}, {"id": "context_chips_directory_fetcher_tests_test_sort_comparison_total_order", "label": "test_sort_comparison_total_order()", "file_type": "code", "source_file": "C:\\Users\\Zero\\Documents\\coding\\Zterm\\app\\src\\context_chips\\directory_fetcher_tests.rs", "source_location": "L11"}, {"id": "context_chips_directory_fetcher_tests_test_sort_same_types_alphabetically", "label": "test_sort_same_types_alphabetically()", "file_type": "code", "source_file": "C:\\Users\\Zero\\Documents\\coding\\Zterm\\app\\src\\context_chips\\directory_fetcher_tests.rs", "source_location": "L64"}, {"id": "context_chips_directory_fetcher_tests_test_sort_single_item", "label": "test_sort_single_item()", "file_type": "code", "source_file": "C:\\Users\\Zero\\Documents\\coding\\Zterm\\app\\src\\context_chips\\directory_fetcher_tests.rs", "source_location": "L97"}], "edges": [{"source": "c_users_zero_documents_coding_zterm_app_src_context_chips_directory_fetcher_tests_rs", "target": "super", "relation": "imports_from", "confidence": "EXTRACTED", "source_file": "C:\\Users\\Zero\\Documents\\coding\\Zterm\\app\\src\\context_chips\\directory_fetcher_tests.rs", "source_location": "L1", "weight": 1.0}, {"source": "c_users_zero_documents_coding_zterm_app_src_context_chips_directory_fetcher_tests_rs", "target": "context_chips_directory_fetcher_tests_create_directory_item", "relation": "contains", "confidence": "EXTRACTED", "source_file": "C:\\Users\\Zero\\Documents\\coding\\Zterm\\app\\src\\context_chips\\directory_fetcher_tests.rs", "source_location": "L3", "weight": 1.0}, {"source": "c_users_zero_documents_coding_zterm_app_src_context_chips_directory_fetcher_tests_rs", "target": "context_chips_directory_fetcher_tests_test_sort_comparison_total_order", "relation": "contains", "confidence": "EXTRACTED", "source_file": "C:\\Users\\Zero\\Documents\\coding\\Zterm\\app\\src\\context_chips\\directory_fetcher_tests.rs", "source_location": "L11", "weight": 1.0}, {"source": "c_users_zero_documents_coding_zterm_app_src_context_chips_directory_fetcher_tests_rs", "target": "context_chips_directory_fetcher_tests_test_sort_same_types_alphabetically", "relation": "contains", "confidence": "EXTRACTED", "source_file": "C:\\Users\\Zero\\Documents\\coding\\Zterm\\app\\src\\context_chips\\directory_fetcher_tests.rs", "source_location": "L64", "weight": 1.0}, {"source": "c_users_zero_documents_coding_zterm_app_src_context_chips_directory_fetcher_tests_rs", "target": "context_chips_directory_fetcher_tests_test_sort_single_item", "relation": "contains", "confidence": "EXTRACTED", "source_file": "C:\\Users\\Zero\\Documents\\coding\\Zterm\\app\\src\\context_chips\\directory_fetcher_tests.rs", "source_location": "L97", "weight": 1.0}], "raw_calls": [{"caller_nid": "context_chips_directory_fetcher_tests_create_directory_item", "callee": "to_string", "is_member_call": true, "source_file": "C:\\Users\\Zero\\Documents\\coding\\Zterm\\app\\src\\context_chips\\directory_fetcher_tests.rs", "source_location": "L5"}, {"caller_nid": "context_chips_directory_fetcher_tests_test_sort_comparison_total_order", "callee": "sort_menu_items", "is_member_call": false, "source_file": "C:\\Users\\Zero\\Documents\\coding\\Zterm\\app\\src\\context_chips\\directory_fetcher_tests.rs", "source_location": "L20"}, {"caller_nid": "context_chips_directory_fetcher_tests_test_sort_comparison_total_order", "callee": "sort_menu_items", "is_member_call": false, "source_file": "C:\\Users\\Zero\\Documents\\coding\\Zterm\\app\\src\\context_chips\\directory_fetcher_tests.rs", "source_location": "L28"}, {"caller_nid": "context_chips_directory_fetcher_tests_test_sort_comparison_total_order", "callee": "sort_menu_items", "is_member_call": false, "source_file": "C:\\Users\\Zero\\Documents\\coding\\Zterm\\app\\src\\context_chips\\directory_fetcher_tests.rs", "source_location": "L36"}, {"caller_nid": "context_chips_directory_fetcher_tests_test_sort_comparison_total_order", "callee": "clone", "is_member_call": true, "source_file": "C:\\Users\\Zero\\Documents\\coding\\Zterm\\app\\src\\context_chips\\directory_fetcher_tests.rs", "source_location": "L48"}, {"caller_nid": "context_chips_directory_fetcher_tests_test_sort_comparison_total_order", "callee": "clone", "is_member_call": true, "source_file": "C:\\Users\\Zero\\Documents\\coding\\Zterm\\app\\src\\context_chips\\directory_fetcher_tests.rs", "source_location": "L49"}, {"caller_nid": "context_chips_directory_fetcher_tests_test_sort_comparison_total_order", "callee": "sort_menu_items", "is_member_call": false, "source_file": "C:\\Users\\Zero\\Documents\\coding\\Zterm\\app\\src\\context_chips\\directory_fetcher_tests.rs", "source_location": "L51"}, {"caller_nid": "context_chips_directory_fetcher_tests_test_sort_comparison_total_order", "callee": "sort_menu_items", "is_member_call": false, "source_file": "C:\\Users\\Zero\\Documents\\coding\\Zterm\\app\\src\\context_chips\\directory_fetcher_tests.rs", "source_location": "L52"}, {"caller_nid": "context_chips_directory_fetcher_tests_test_sort_same_types_alphabetically", "callee": "sort_menu_items", "is_member_call": false, "source_file": "C:\\Users\\Zero\\Documents\\coding\\Zterm\\app\\src\\context_chips\\directory_fetcher_tests.rs", "source_location": "L70"}, {"caller_nid": "context_chips_directory_fetcher_tests_test_sort_same_types_alphabetically", "callee": "sort_menu_items", "is_member_call": false, "source_file": "C:\\Users\\Zero\\Documents\\coding\\Zterm\\app\\src\\context_chips\\directory_fetcher_tests.rs", "source_location": "L80"}, {"caller_nid": "context_chips_directory_fetcher_tests_test_sort_same_types_alphabetically", "callee": "sort_menu_items", "is_member_call": false, "source_file": "C:\\Users\\Zero\\Documents\\coding\\Zterm\\app\\src\\context_chips\\directory_fetcher_tests.rs", "source_location": "L90"}, {"caller_nid": "context_chips_directory_fetcher_tests_test_sort_single_item", "callee": "sort_menu_items", "is_member_call": false, "source_file": "C:\\Users\\Zero\\Documents\\coding\\Zterm\\app\\src\\context_chips\\directory_fetcher_tests.rs", "source_location": "L99"}]}